akismet/__init__.py
akismet/client.py
akismet/entities.py
akismet/exceptions.py
akismet_async-0.0.1.dist-info/WHEEL
akismet_async-0.0.1.dist-info/METADATA
akismet_async-0.0.1.dist-info/RECORD
