Metadata-Version: 2.1
Name: akismet-async
Version: 0.0.1
Summary: An async Python interface to the Akismet API.
Home-page: https://github.com/arni-inaba/akismet-async
License: MIT
Author: Arni Inaba Kjartansson
Author-email: arni@inaba.is
Requires-Python: >=3.7,<4.0
Classifier: License :: OSI Approved :: MIT License
Classifier: Programming Language :: Python :: 3
Classifier: Programming Language :: Python :: 3.10
Classifier: Programming Language :: Python :: 3.7
Classifier: Programming Language :: Python :: 3.8
Classifier: Programming Language :: Python :: 3.9
Requires-Dist: httpx (>=0.22.0,<0.23.0)
Requires-Dist: strenum (==0.4.7)
Project-URL: Repository, https://github.com/arni-inaba/akismet-async
